{
  "entry": "server.js",
  "files": {
    "0b6bd286f69f8e0f3e07.js": "0b6bd286f69f8e0f3e07.js",
    "6050f0179be4d2de4950.js": "6050f0179be4d2de4950.js",
    "69f1785e22537aaff3bd.js": "69f1785e22537aaff3bd.js",
    "9f2001bbd4ed76496753.js": "9f2001bbd4ed76496753.js",
    "e1c2d310f6b68ac65cc2.js": "e1c2d310f6b68ac65cc2.js",
    "server.js": "server.js"
  },
  "maps": {
    "0b6bd286f69f8e0f3e07.js": "0b6bd286f69f8e0f3e07.js.map",
    "6050f0179be4d2de4950.js": "6050f0179be4d2de4950.js.map",
    "69f1785e22537aaff3bd.js": "69f1785e22537aaff3bd.js.map",
    "9f2001bbd4ed76496753.js": "9f2001bbd4ed76496753.js.map",
    "e1c2d310f6b68ac65cc2.js": "e1c2d310f6b68ac65cc2.js.map",
    "server.js": "server.js.map"
  }
}